edc_form_runners/__init__.py
edc_form_runners/admin_site.py
edc_form_runners/apps.py
edc_form_runners/auth_objects.py
edc_form_runners/auths.py
edc_form_runners/decorators.py
edc_form_runners/exceptions.py
edc_form_runners/form_runner.py
edc_form_runners/form_runner_by_scr_id.py
edc_form_runners/get_form_runner.py
edc_form_runners/get_form_runner_by_src_id.py
edc_form_runners/run_form_runners.py
edc_form_runners/site.py
edc_form_runners/urls.py
edc_form_runners/utils.py
edc_form_runners/admin/__init__.py
edc_form_runners/admin/actions.py
edc_form_runners/admin/issue_admin.py
edc_form_runners/management/__init__.py
edc_form_runners/management/commands/__init__.py
edc_form_runners/management/commands/run_form_runners.py
edc_form_runners/migrations/0001_initial.py
edc_form_runners/migrations/0002_alter_issue_options_and_more.py
edc_form_runners/migrations/0003_alter_issue_visit_code_and_more.py
edc_form_runners/migrations/__init__.py
edc_form_runners/models/__init__.py
edc_form_runners/models/issue.py
edc_form_runners/models/signals.py
edc_form_runners/templates/edc_form_runners/form_runner_issues.html
edc_form_runners/templatetags/__init__.py
edc_form_runners/templatetags/form_runners_extras.py
edc_form_runners/tests/__init__.py
edc_form_runners/tests/holidays.csv
edc_form_runners/tests/test_settings.py
edc_form_runners/tests/etc/user-aes-local.key
edc_form_runners/tests/etc/user-aes-restricted.key
edc_form_runners/tests/etc/user-rsa-local-private.pem
edc_form_runners/tests/etc/user-rsa-local-public.pem
edc_form_runners/tests/etc/user-rsa-restricted-private.pem
edc_form_runners/tests/etc/user-rsa-restricted-public.pem
edc_form_runners/tests/etc/user-salt-local.key
edc_form_runners/tests/etc/user-salt-restricted.key
edc_form_runners/tests/tests/__init__.py
edc_form_runners/tests/tests/test_runners.py
form_runners_app/__init__.py
form_runners_app/admin.py
form_runners_app/apps.py
form_runners_app/consents.py
form_runners_app/forms.py
form_runners_app/models.py
edc_form_runners-1.0.0.dist-info/AUTHORS
edc_form_runners-1.0.0.dist-info/LICENSE
edc_form_runners-1.0.0.dist-info/METADATA
edc_form_runners-1.0.0.dist-info/WHEEL
edc_form_runners-1.0.0.dist-info/top_level.txt
edc_form_runners-1.0.0.dist-info/RECORD
